infoFlib/Functions.py
infoFlib/Lib.py
infoFlib/__init__.py
infoFlib-1.0.1.dist-info/METADATA
infoFlib-1.0.1.dist-info/WHEEL
infoFlib-1.0.1.dist-info/top_level.txt
infoFlib-1.0.1.dist-info/RECORD
