Metadata-Version: 2.1
Name: infoFlib
Version: 1.0.1
Summary: Biblioteca para registro de usuários, livros, locação e devolução
Home-page: https://github.com/Lursy7/infoFlib
Author: Lursy
Author-email: matheus.cruz@alunos.ifsuldeminas.edu.br
Classifier: Development Status :: 5 - Production/Stable
Classifier: Intended Audience :: Developers
Classifier: License :: OSI Approved :: MIT License
Classifier: Programming Language :: Python :: 3
Classifier: Programming Language :: Python :: 3.6
Classifier: Programming Language :: Python :: 3.7
Classifier: Programming Language :: Python :: 3.8
Classifier: Programming Language :: Python :: 3.9
Requires-Dist: pyfiglet ==0.8.post1
